ensembl_prodinf_core-3.0.0-py3.10-nspkg.pth
ensembl/production/core/amqp_publishing.py
ensembl/production/core/app_logging.py
ensembl/production/core/config.py
ensembl/production/core/db_introspects.py
ensembl/production/core/db_utils.py
ensembl/production/core/es.py
ensembl/production/core/exceptions.py
ensembl/production/core/perl_utils.py
ensembl/production/core/reporting.py
ensembl/production/core/resource_lock.py
ensembl/production/core/rest.py
ensembl/production/core/server_utils.py
ensembl/production/core/utils.py
ensembl/production/core/clients/__init__.py
ensembl/production/core/clients/datachecks.py
ensembl/production/core/clients/dbcopy.py
ensembl/production/core/clients/event.py
ensembl/production/core/clients/genomemetadata.py
ensembl/production/core/clients/handover.py
ensembl/production/core/clients/metadata.py
ensembl/production/core/models/__init__.py
ensembl/production/core/models/compara.py
ensembl/production/core/models/core.py
ensembl/production/core/models/hive.py
ensembl/production/core/templates/ensembl/base.html
ensembl/production/core/templates/ensembl/detail.html
ensembl/production/core/templates/ensembl/index.html
ensembl/production/core/templates/ensembl/list.html
ensembl/production/core/templates/ensembl/submit.html
ensembl/production/core/templates/flasgger/custom_head.html
test/sample_config.yaml
test/test_db_introspects.py
test/test_es.py
test/test_hive.py
test/test_locking.py
test/test_perl_parsing.py
test/test_pipeline.db.template
test/test_server_utils.py
test/test_utils.py
test/test_yaml.py
test/perl/TestFactory.pm
test/perl/TestPipeline_conf.pm
test/perl/TestRunnable.pm
test/perl/TestRunnableDecorate.pm
test/perl/TestRunnableMerge.pm
test/perl/TestRunnableParallel.pm
ensembl_prodinf_core-3.0.0.dist-info/LICENSE
ensembl_prodinf_core-3.0.0.dist-info/METADATA
ensembl_prodinf_core-3.0.0.dist-info/WHEEL
ensembl_prodinf_core-3.0.0.dist-info/namespace_packages.txt
ensembl_prodinf_core-3.0.0.dist-info/top_level.txt
ensembl_prodinf_core-3.0.0.dist-info/RECORD
